aiorouter/__init__.py
aiorouter/router_manager.py
aiorouter-0.1.0.dist-info/METADATA
aiorouter-0.1.0.dist-info/WHEEL
aiorouter-0.1.0.dist-info/top_level.txt
aiorouter-0.1.0.dist-info/RECORD
