Metadata-Version: 2.1
Name: aiorouter
Version: 0.1.0
Summary: Library to manage aiogram routers more easily.
Author: @vanya_developer
Classifier: Programming Language :: Python :: 3
Classifier: License :: OSI Approved :: MIT License
Classifier: Operating System :: OS Independent
Requires-Python: >=3.7
Requires-Dist: aiogram >=3.0.0
